assembl/__init__.py
assembl/conftest.py
assembl/fabfile.py
assembl/maintenance.py
assembl/utils.py
assembl/validation.py
assembl/alembic/env.py
assembl/alembic/versions/025d088eb45a_langstring_on_ideamessagecolumn.py
assembl/alembic/versions/053f788ca313_resource_center.py
assembl/alembic/versions/06a588c53002_attachments_from_youtube_inspiration.py
assembl/alembic/versions/074316d2e8a8_add_user_machine.py
assembl/alembic/versions/083c79582c91_update_multimedia_module.py
assembl/alembic/versions/0888e0f1a92d_timeline.py
assembl/alembic/versions/10159cb599ff_add_votes.py
assembl/alembic/versions/104d2f466913_social_email.py
assembl/alembic/versions/10d81337e9f1_proposal_post.py
assembl/alembic/versions/11d73c586596_token_votes.py
assembl/alembic/versions/12fd3dd74340_widgets_table.py
assembl/alembic/versions/134299d407b9_add_extract_lang.py
assembl/alembic/versions/13cb36c87aea_ancestry_index.py
assembl/alembic/versions/14296672081d_longer_preferred_email.py
assembl/alembic/versions/14e5db4fde8e_add_tables_needed_for_phase_1.py
assembl/alembic/versions/157237dd5620_add_content_source_error_notification.py
assembl/alembic/versions/1593228f01ab_hopefully_fix_duplicate_imported_.py
assembl/alembic/versions/163294913218_import_records.py
assembl/alembic/versions/165e8b786ca0_vote_spec_question_id_nullable.py
assembl/alembic/versions/172cd43879ac_ideacontentwidgetlink_are_positive_links.py
assembl/alembic/versions/180022eb0f0d_add_extract_hash.py
assembl/alembic/versions/187cdadb065f_add_participant_templates_to_existing_.py
assembl/alembic/versions/1931a5603650_store_mime_type_of_post_body.py
assembl/alembic/versions/19b28b9ea376_migrate_facebook_users.py
assembl/alembic/versions/19db6b12a1e9_role_request.py
assembl/alembic/versions/1bbe7758d93e_unicode_social_username.py
assembl/alembic/versions/1c09e0b1ff2a_add_announces.py
assembl/alembic/versions/1e01b5f0e5f9_file_upload.py
assembl/alembic/versions/1e1d2b26db86_discussionkvpairs.py
assembl-2.16.0.dist-info/LICENSE.txt
assembl-2.16.0.dist-info/METADATA
assembl-2.16.0.dist-info/WHEEL
assembl-2.16.0.dist-info/dependency_links.txt
assembl-2.16.0.dist-info/entry_points.txt
assembl-2.16.0.dist-info/top_level.txt
assembl-2.16.0.dist-info/RECORD
