Metadata-Version: 2.1
Name: assembl
Version: 2.16.0
Summary: Collective Intelligence platform
Home-page: http://assembl.org/
Author: 
Author-email: 
License: AGPLv3
Keywords: web wsgi pyramid
Platform: UNKNOWN
Classifier: Programming Language :: Python :: 2.7
Classifier: Programming Language :: JavaScript
Classifier: Framework :: Pyramid
Classifier: Topic :: Communications
Classifier: Topic :: Internet :: WWW/HTTP
Classifier: Topic :: Internet :: WWW/HTTP :: Dynamic Content :: Message Boards
Classifier: Topic :: Internet :: WWW/HTTP :: WSGI :: Application
Classifier: License :: OSI Approved :: GNU Affero General Public License v3
Requires-Dist: zope.sqlalchemy (==0.7.7)
Requires-Dist: pip-tools (==1.11.0)
Requires-Dist: polib (==1.0.7)
Requires-Dist: premailer (==3.0.0)
Requires-Dist: anyjson (==0.3.3)
Requires-Dist: Fabric (==1.14.0)
Requires-Dist: lingua (==4.9)
Requires-Dist: uwsgitop (==0.9)
Requires-Dist: feedparser (==5.2.1)
Requires-Dist: iso639 (==0.1.4)
Requires-Dist: openpyxl (==2.4.1)
Requires-Dist: python-json-logger (==0.1.8)
Requires-Dist: graphql-relay (==0.4.5)
Requires-Dist: ndg-httpsclient (==0.5.1)
Requires-Dist: Jinja2 (==2.8)
Requires-Dist: hiredis (==0.2.0)
Requires-Dist: simplejson (==3.8.2)
Requires-Dist: celery (==4.1.1)
Requires-Dist: graphene (==1.4.1)
Requires-Dist: social-auth-storage-sqlalchemy (==1.1.0)
Requires-Dist: requests (==2.10.0)
Requires-Dist: graphql-core (==1.1.0)
Requires-Dist: imaplib2 (==2.45.0)
Requires-Dist: structlog (==17.2.0)
Requires-Dist: verboselogs (==1.7)
Requires-Dist: social-auth-core (==1.7.0)
Requires-Dist: pyopenssl (==18.0)
Requires-Dist: graphene-sqlalchemy (==1.1.1)
Requires-Dist: pyramid-jinja2 (==2.6.2)
Requires-Dist: supervisor (==3.3.0)
Requires-Dist: ipython (==4.2.0)
Requires-Dist: transaction (==1.6.1)
Requires-Dist: flaky (==3.1.1)
Requires-Dist: lxml (==4.2.5)
Requires-Dist: redis (==2.10.5)
Requires-Dist: pyIsEmail
Requires-Dist: Babel (==2.3.4)
Requires-Dist: pytz (==2016.4)
Requires-Dist: rotate-backups (==4.4)
Requires-Dist: SQLAlchemy (==1.2.2)
Requires-Dist: requests-oauthlib (==0.6.1)
Requires-Dist: alembic (==0.8.6)
Requires-Dist: isodate (==0.5.4)
Requires-Dist: nodeenv (==1.3.0)
Requires-Dist: pyramid-mailer (==0.14.1)
Requires-Dist: Unidecode (==0.4.19)
Requires-Dist: social-auth-app-pyramid (==1.0.0)
Requires-Dist: six (==1.10.0)
Requires-Dist: beautifulsoup4 (==4.6.0)
Requires-Dist: pyramid (==1.7)
Requires-Dist: pyzmq (==15.2.0)
Requires-Dist: zope.component (==4.2.2)
Requires-Dist: dogpile.cache (==0.6.7)
Requires-Dist: tornado (==4.3)
Requires-Dist: PyStemmer (==1.3.0)
Requires-Dist: WebOb (==1.6.1)
Requires-Dist: jsonpath-ng (==1.4.3)
Requires-Dist: enum34 (==1.1.6)
Requires-Dist: pyramid-tm (==0.12.1)
Requires-Dist: python-dateutil (==2.5.3)
Requires-Dist: zope.interface (==4.2.0)
Requires-Dist: pylibmc (==1.5.1)
Requires-Dist: psycopg2 (==2.7.3.1)
Requires-Dist: coloredlogs (==7.3)
Requires-Dist: PyJWT (==1.4.0)
Requires-Dist: translationstring (==1.3)
Requires-Dist: future (==0.15.2)
Requires-Dist: python-saml (==2.4.2)
Requires-Dist: elasticsearch (==5.1.0)
Requires-Dist: pyramid-ipython (==0.1)
Requires-Dist: google-api-python-client (==1.6.6)
Requires-Dist: ColanderAlchemy (==0.3.3)
Requires-Dist: raven (==6.9.0)
Requires-Dist: colander (==1.3.1)
Requires-Dist: Werkzeug (==0.11.10)
Requires-Dist: colorama (==0.3.9)
Provides-Extra: dev
Requires-Dist: pyramid-debugtoolbar-ajax (==0.0.4); extra == 'dev'
Requires-Dist: pre-commit (==1.8.2); extra == 'dev'
Requires-Dist: flake8 (==3.5.0); extra == 'dev'
Requires-Dist: PdbSublimeTextSupport (==0.2); extra == 'dev'
Requires-Dist: pyramid-debugtoolbar (==3.0.1); extra == 'dev'
Provides-Extra: docs
Requires-Dist: Sphinx (==1.5.1); extra == 'docs'
Requires-Dist: sphinxcontrib-zopeext (==0.2.1); extra == 'docs'
Requires-Dist: sqlalchemy-schemadisplay (==1.3); extra == 'docs'
Requires-Dist: sphinxcontrib-httpdomain (==1.5.0); extra == 'docs'
Requires-Dist: pyramid-autodoc (==1.0.0); extra == 'docs'
